Metadata-Version: 2.1
Name: Discus-Synthetics
Version: 0.1.0b0
Summary: A package containing everything you need to finetune your LLMs
Author: Discus Founders
Author-email: founders@discus.ai
License-File: LICENSE
